karaoke_generator/__init__.py
karaoke_generator/generator.py
karaoke_generator/utils/__init__.py
karaoke_generator/utils/cli.py
karaoke_generator-0.6.0.dist-info/METADATA
karaoke_generator-0.6.0.dist-info/WHEEL
karaoke_generator-0.6.0.dist-info/entry_points.txt
karaoke_generator-0.6.0.dist-info/RECORD
