Metadata-Version: 2.1
Name: karaoke-generator
Version: 0.6.0
Summary: Fully automated creation of _acceptable_ karaoke music videos from any music on YouTube, using open source tools and AI (e.g. Whisper and MDX-Net)
Home-page: https://github.com/karaokenerds/karaoke-generator
License: MIT
Author: Andrew Beveridge
Author-email: andrew@beveridge.uk
Requires-Python: >=3.9
Classifier: License :: OSI Approved :: MIT License
Classifier: Programming Language :: Python :: 3
Classifier: Programming Language :: Python :: 3.9
Classifier: Programming Language :: Python :: 3.10
Classifier: Programming Language :: Python :: 3.11
Classifier: Programming Language :: Python :: 3.12
Requires-Dist: audio-separator (>=0.6)
Requires-Dist: lyrics-transcriber (>=0.16)
Requires-Dist: pydub (>=0.25)
Requires-Dist: python-slugify (>=8)
Requires-Dist: regex (>=2023)
Requires-Dist: tldextract (>=3)
Requires-Dist: yt-dlp (>=2024.07.09)
Project-URL: Documentation, https://github.com/karaokenerds/karaoke-generator/blob/main/README.md
Project-URL: Repository, https://github.com/karaokenerds/karaoke-generator
